{"cameraMode":{"drawMode":0,"name":"Shaded","section":"Shading Mode"},"sceneLighting":false,"audioPlay":false,"sceneViewState":{"showFog":true,"showMaterialUpdate":true,"showSkybox":false,"showFlares":true,"showImageEffects":true,"showParticleSystems":true,"showVisualEffectGraphs":true,"m_FxEnabled":true},"in2DMode":false,"pivot":{"x":-2.947730541229248,"y":3.5852954387664797,"z":-6.263346195220947},"rotation":{"x":-0.04801810532808304,"y":-0.8697776198387146,"z":0.08639039099216461,"w":-0.48344576358795168},"size":1.1316413879394532,"orthographic":false}